markdown_vidify/__init__.py
markdown_vidify/markdown_vidify.py
test/__init__.py
test/test_vidify.py
vidify/__init__.py
vidify/vidify.py
markdown_vidify-0.1.2.dist-info/LICENSE
markdown_vidify-0.1.2.dist-info/METADATA
markdown_vidify-0.1.2.dist-info/WHEEL
markdown_vidify-0.1.2.dist-info/entry_points.txt
markdown_vidify-0.1.2.dist-info/top_level.txt
markdown_vidify-0.1.2.dist-info/RECORD
