Metadata-Version: 2.1
Name: markdown-vidify
Version: 0.1.2
Summary: Video tag generator markdown extension
Home-page: https://github.com/zchfvy/vidify
Author: Jason Hamilton-Smith
Maintainer: Jason Hamilton-Smith
Maintainer-email: hs.jason@gmail.com
License: GPLv3
Keywords: makrdown video html5 html5video
Platform: UNKNOWN
Classifier: Intended Audience :: Developers
Classifier: Programming Language :: Python
Classifier: Programming Language :: Python :: 2
Classifier: Programming Language :: Python :: 2.7
Classifier: Programming Language :: Python :: 3
Classifier: Programming Language :: Python :: 3.6
Classifier: Topic :: Documentation
Classifier: Topic :: Text Processing :: Markup
Requires-Python: >=2.7.15, !=3.0.*, !=3.1.*, !=3.2.*, !=3.3.*, !=3.4.*, !=3.5.*
Requires-Dist: markdown (<4,>=3.2.1)
